{
    "movie":[
        {
            "id": 1,
            "name": "王牌逗王牌",
            "year": 2016,
            "country": "中国大陆/香港",
            "type": [
                "喜剧",
                "动作",
                "冒险"
            ],
            "imgUrl": "/images/wangpaidouwangpai.jpg",
            "language": "汉语普通话",
            "showUpDate": "2016-09-30",
            "director": "王晶",
            "mainActor": [
                "刘德华",
                "黄晓明"
            ],
            "contentDetail": "囧探宝爷（刘德华 饰）与侠盗洛家豪（黄晓明 饰）强强联手，与世界恐怖组织抢夺“上帝种子”，所谓“上帝种子”是一种神奇的种子，无论丢在哪里，只需要一点水，就可以迅速长出参天大树。而唯恐天下不乱的恐怖组织居然拿到了这种神奇的“上帝种子”，试图改变甚至掌控这个世界。为了维护世界和平，宝爷和家豪在A梦（王祖蓝 饰）、洛家欣（欧阳娜娜 饰）等人的帮助下，冒险夺宝拯救世界的故事。"
        },
        {
            "id": 2,
            "name": "谍影重重5",
            "year": 2016,
            "country": "美国",
            "type": [
                "动作",
                "悬疑",
                "惊悚"
            ],
            "imgUrl": "/images/dieyingchongchong5.jpg",
            "language": "英语",
            "showUpDate": "2016-08-23",
            "director": "保罗·格林格拉斯",
            "mainActor": [
                "马特·达蒙"
            ],
            "contentDetail": "影片故事发生在后斯诺登时代，中情局系统被黑客入侵， 多项特工计划可能泄露。与此同时，中情局还发现了伯恩和好搭档尼基·帕森斯的踪迹。年轻的网络专家海瑟·李自告奋勇追踪伯恩，而伯恩也在寻找着关于自己身世的惊天黑幕。中情局高官杜威是知晓一切幕后秘密的人，他、海瑟·李和伯恩之间的角力让影片充满悬念，不到最后一刻，就无法了解真正的结局。"
        },
        {
            "id": 3,
            "name": "搏击之王",
            "year": 2016,
            "country": "美国",
            "type": [
                "动作"
            ],
            "imgUrl": "/images/bojizhiwang.jpg",
            "language": "英语",
            "showUpDate": "2016-09-02",
            "director": "约翰·斯托克韦尔",
            "mainActor": [
                "戴夫·巴蒂斯塔"
            ],
            "contentDetail": "埃里克和斯隆出生自一个享誉盛名的威尼斯家族，加利福尼亚本土著名的拳击家族，斯隆一直生活在哥哥埃里克的身影下，但他渴望成为哥哥那样的拳击高手，埃里克因为巨额奖金前往泰国而死在泰拳手唐的手里，为了为哥哥复仇捍卫家族荣誉，埃里克开始的地狱般的训练。"
        },
        {
            "id": 4,
            "name": "阿修罗",
            "year": 2016,
            "country": "韩国",
            "type": [
                "剧情",
                "动作",
                "犯罪"
            ],
            "imgUrl": "/images/axiuluo.jpg",
            "language": "韩语",
            "showUpDate": "2016-09-28",
            "director": "金成洙",
            "mainActor": [
                "郑雨盛","黄政名"
            ],
            "contentDetail": "身处台风眼的刑警韩度京（郑雨盛饰），夹在朴成裴市长（黄政民饰）和调查他的刑警队之间，为了自己的生存而不择手段。片中最大的反派朴成裴市长，为了追求私利而无所不为。刑警文先模（朱智勋饰），在韩度京的命令下，接近朴市长担任卧底工作。另一方面，特殊监察支队的检察官金车仁（郭道元饰）也在调查着朴成裴市长，个心狠手辣的角色。韩度京为了取得成功而不惜为市长朴成裴的各种犯罪活动做善后，并从中收取报酬。韩度京得知妻子身患癌症后，以筹措医疗费用为借口，赚钱不计手段，渐渐偏离了警察的职业道德，走上歪路。负责特种案件的检察官金车仁手里攥着韩度京的弱点，刑警调查队队长都昌学（郑万植饰）也为了获取朴成裴的犯罪证据而威胁韩度京。后辈刑警文先模，视韩度京如亲哥哥，打进朴成裴团伙做卧底工作。韩度京处于两种势力之间进退维谷，此时的文先模也慢慢被腐蚀。就这样，几个男人各自为了生存厮杀，他们之间没有最坏，只有谁更坏。"
        },
        {
            "id": 5,
            "name": "流氓督察2",
            "year": 2016,
            "country": "印度",
            "type": [
                "喜剧","动作"
            ],
            "imgUrl": "/images/liumangjingcha2.jpg",
            "language": "印度语",
            "showUpDate": "2016",
            "director": "暂无",
            "mainActor": [
                "暂无"
            ],
            "contentDetail": "An Empire called Rathan pur was taken ruthlessly by a feudal lord named Bhairav Singh. The princess of that empire was in a helpless situation. To overcome those problems a mevric cop named Sarddr Gabbar Singh comes and clears the issue."
        },
        {
            "id": 6,
            "name": "使徒行者",
            "year": 2016,
            "country": "中国香港",
            "type": [
                "剧情","犯罪","动作"
            ],
            "imgUrl": "/images/shituxingzhe.jpg",
            "language": "粤语/国语",
            "showUpDate": "2016",
            "director": "文伟鸿",
            "mainActor": [
                "张家辉","吴镇宇"
            ],
            "contentDetail": "使徒行者电影版讲述女卧底阿钉（畲诗曼 饰）收到一个以康氏密码打出的神秘讯息，一个自称「Blackjack」的卧底表示跟警队失联，阿钉随即报告上司Q Sir（吴镇宇 饰），一轮「寻找卧底」行动立即展开。过程里，阿钉被引到赌场，竟发现当年被枪杀的覃欢喜「死而复生」。同一时间，Q Sir查得某商业集团暗地里涉足一宗巴西毒品交易，始把「Blackjack」的所在位置收窄，而牵涉交易的人物包括：集团主席郭铭，谋臣阿蓝（张家辉 饰），阿蓝头马少爷（古天乐 饰），以及欲东山再起的覃欢喜等。此时，各人开始知晓有卧底潜伏，人人开始猜疑，人人自危⋯"
        },
        {
            "id": 7,
            "name": "绝地逃亡",
            "year": 2016,
            "country": "中国大陆/美国",
            "type": [
                "喜剧","动作"
            ],
            "imgUrl": "/images/jueditaowang.jpg",
            "language": "汉语普通话/英语",
            "showUpDate": "2016-07-21",
            "director": "雷尼·哈林",
            "mainActor": [
                "成龙","范冰冰"
            ],
            "contentDetail": "香港探员陈港生（成龙饰）跟踪黑道老大维克多·王（赵文瑄饰）长达十数年，为搜集他犯罪证据而被卷入一场“计中计”中，还将自己的侄女白舒（范冰冰饰）牵扯进来。在这场被中国特警、维克多·王、俄罗斯黑帮三面夹攻的“绝地逃亡”中，班尼结识了共患难的最佳拍档康纳（约翰尼·诺克斯维尔饰），一位正被维克多·王和俄国杀手追捕逃命的美国赌博高手，三人最终将怎样结束这场冒险变得扑朔迷离。"
        },
        {
            "id": 8,
            "name": "绝路反击",
            "year": 2016,
            "country": "西班牙",
            "type": [
                "犯罪","惊悚"
            ],
            "imgUrl": "/images/juedifanji.jpg",
            "language": "西班牙语",
            "showUpDate": "2016-04-22",
            "director": "凯克·麦罗",
            "mainActor": [
                "马里奥·卡萨斯","路伊斯·托沙"
            ],
            "contentDetail": "五年前犯案时失手，三兄弟中Toro锒铛入狱， 一人丧命，另外Antonio失踪。出狱一刻Toro决定远离过去，重新做人，但Antonio带同他的小女儿突然现身，原来欠下黑帮大佬巨款，要求协助。三人被迫开始一段危险的逃亡之旅，直至走投无路，兄弟和解，合力与敌人拼过！"
        },
        {
            "id": 9,
            "name": "超能敢死队",
            "year": 2016,
            "country": "美国",
            "type": [
                "动作","喜剧","惊悚"
            ],
            "imgUrl": "/images/chaonenggansidui.jpg",
            "language": "英语",
            "showUpDate": "2016-07-15",
            "director": "保罗·费格",
            "mainActor": [
                "梅丽莎·麦卡西","克里斯汀·韦格"
            ],
            "contentDetail": "哥伦毕业大学教授Erin Gilbert（克里斯汀·韦格 Kristen Wiig 饰）和Abby Yates（梅丽莎·麦卡西 Melissa McCarthy 饰）是合作愉快的作家。如今，为了告诉人们“幽灵是存在的”，她们将一起编著一本关于幽灵的书籍。当对“鬼魂”的深入研究中，当“鬼魂”入侵她们所居住的城市时，她们和另外两个搭档Jillian Holtzmann（凯特·麦克金农 Kate McKinnon 饰）、Patty Tolan（莱斯莉·琼斯 Leslie Jones 饰）一起投入到拯救城市、拯救世界的行动中……"
        },
        {
            "id": 10,
            "name": "大话西游3",
            "year": 2016,
            "country": "中国大陆",
            "type": [
                "爱情","喜剧","奇幻"
            ],
            "imgUrl": "/images/dahuaxiyou3.jpg",
            "language": "汉语普通话",
            "showUpDate": "2016-09-14",
            "director": "刘镇伟",
            "mainActor": [
                "韩庚","唐嫣"
            ],
            "contentDetail": "在《大话西游之大圣娶亲》中死在牛魔王叉下的紫霞仙子（唐嫣 饰），将会通过月光宝盒预先看到这一下场，为了避免惨剧发生，她选择回到从前不让至尊宝（韩庚 饰）爱上自己。而至尊宝又再次重逢一直在等待他的白晶晶（莫文蔚 饰）。前世今生的种种爱恨纠葛再次在九道轮回里最后一次上演。"
        },
        {
            "id": 11,
            "name": "湄公河行动",
            "year": 2016,
            "country": "中国大陆",
            "type": [
                "犯罪","动作"
            ],
            "imgUrl": "/images/meigonghexingdong.jpg",
            "language": "汉语普通话",
            "showUpDate": "2016-09-30",
            "director": "林超贤",
            "mainActor": [
                "张涵予","彭于晏"
            ],
            "contentDetail": "2011年10月5日，两艘中国商船在湄公河金三角水域遭遇袭击，13名中国船员全部遇难，泰国警方从船上搜出90万颗电影下载。消息传回国内，举国震惊。为了查明真相，云南缉毒总队长高刚（张涵予 饰）接受了特殊任务，率领一支骁勇善战的战斗小组进入泰国境内，与潜伏在泰国的情报员方新武（彭于晏 饰）碰头，二人联手深入金三角查案。经过调查，发现案件背后果然有着重重疑点，真正的凶手在嫁祸残害无辜中国船员后，不但逍遥法外，更意图利用毒品制造更大的阴谋……二人决定，不惜一切代价也要拿下真凶，打击毒品犯罪，为无辜国人讨回公道！"
        },
        {
            "id": 12,
            "name": "人类清除计划",
            "year": 2016,
            "country": "美国",
            "type": [
                "科幻","动作","恐怖"
            ],
            "imgUrl": "/images/renleiqingchujihua.jpg",
            "language": "俄语/英语",
            "showUpDate": "暂无",
            "director": "詹姆斯·德莫纳克",
            "mainActor": [
                "弗兰克·格里罗","伊丽莎白·米切尔"
            ],
            "contentDetail": "一年一度的国定杀戮日即将到来，与此同时，美国总统大选也到了如火如荼的阶段，一方是创立并推行国定杀戮日的NFFA的代言人艾德维奇?欧文斯，一方则是曾被这个可怕的杀戮夺走家人的女参议员查理·罗恩（伊丽莎白·米切尔 Elizabeth Mitchell 饰）。查理不惜一切代价要将国定杀戮日废止，因此成为了NFFA的眼中钉，对方策划在杀戮之夜夺走她的性命。刚强的查理坚持当晚待在家中，而她的安全主管里奥（弗兰克·格里罗 Frank Grillo 饰）则打起十二分的精神准备应对四面八方的对手。"
        }
    ]
}